CHANGES.rst
CONTRIBUTING.rst
LICENSE
MANIFEST.in
README.rst
setup.py
extras/wifi-completion.bash
wifi/__init__.py
wifi/__main__.py
wifi/cli.py
wifi/exceptions.py
wifi/scan.py
wifi/scheme.py
wifi/subprocess_compat.py
wifi/utils.py
wifi_roboticia.egg-info/PKG-INFO
wifi_roboticia.egg-info/SOURCES.txt
wifi_roboticia.egg-info/dependency_links.txt
wifi_roboticia.egg-info/entry_points.txt
wifi_roboticia.egg-info/requires.txt
wifi_roboticia.egg-info/top_level.txt